opensearch_sql_cli/__init__.py
opensearch_sql_cli/config.py
opensearch_sql_cli/formatter.py
opensearch_sql_cli/main.py
opensearch_sql_cli/opensearch_buffer.py
opensearch_sql_cli/opensearch_connection.py
opensearch_sql_cli/opensearch_style.py
opensearch_sql_cli/opensearchsql_cli.py
opensearch_sql_cli/utils.py
opensearch_sql_cli/conf/__init__.py
opensearch_sql_cli/conf/clirc
opensearch_sql_cli/opensearch_literals/__init__.py
opensearch_sql_cli/opensearch_literals/opensearch_literals.json
opensearchsql-1.0.0.dist-info/LICENSE.TXT
opensearchsql-1.0.0.dist-info/METADATA
opensearchsql-1.0.0.dist-info/NOTICE
opensearchsql-1.0.0.dist-info/WHEEL
opensearchsql-1.0.0.dist-info/entry_points.txt
opensearchsql-1.0.0.dist-info/top_level.txt
opensearchsql-1.0.0.dist-info/RECORD
