Metadata-Version: 2.1
Name: opensearchsql
Version: 1.0.0
Summary: OpenSearch SQL CLI with auto-completion and syntax highlighting
Home-page: https://docs-beta.opensearch.org/search-plugins/sql/cli/
Author: OpenSearch
Author-email: opensearch-infra@amazon.com
License: Apache 2.0
Platform: UNKNOWN
Classifier: Intended Audience :: Developers
Classifier: License :: OSI Approved :: Apache Software License
Classifier: Operating System :: Unix
Classifier: Operating System :: POSIX :: Linux
Classifier: Programming Language :: Python
Classifier: Programming Language :: Python :: 3
Classifier: Programming Language :: Python :: 3.4
Classifier: Programming Language :: Python :: 3.5
Classifier: Programming Language :: Python :: 3.6
Classifier: Programming Language :: Python :: 3.7
Classifier: Programming Language :: Python :: 3.8
Classifier: Programming Language :: SQL
Classifier: Topic :: Database
Classifier: Topic :: Database :: Front-Ends
Classifier: Topic :: Software Development
Classifier: Topic :: Software Development :: Libraries :: Python Modules
Requires-Python: >=3.0
License-File: LICENSE.TXT
License-File: NOTICE
Requires-Dist: click (==7.1.1)
Requires-Dist: prompt-toolkit (==2.0.6)
Requires-Dist: Pygments (==2.11.1)
Requires-Dist: cli-helpers[styles] (==1.2.1)
Requires-Dist: opensearch-py (==1.0.0)
Requires-Dist: pyfiglet (==0.8.post1)
Requires-Dist: boto3 (==1.16.29)
Requires-Dist: requests-aws4auth (==0.9)
